{
    "clientName": "Thunder Client",
    "collectionName": "Authentication",
    "collectionId": "66c6f162-c303-44d8-9ad3-b3a6641d2b80",
    "dateExported": "2025-03-15T13:46:42.860Z",
    "version": "1.2",
    "folders": [],
    "requests": [
        {
            "_id": "22e3b311-5306-4ec5-9731-719af98b7be0",
            "colId": "66c6f162-c303-44d8-9ad3-b3a6641d2b80",
            "containerId": "",
            "name": "createuser",
            "url": "http://localhost:3000/api/auth/createuser",
            "method": "POST",
            "sortNum": 10000,
            "created": "2025-03-15T07:46:26.726Z",
            "modified": "2025-03-15T07:48:37.620Z",
            "headers": [],
            "body": {
                "type": "json",
                "raw": "{\n  \"name\": \"donald tatya\",\n  \"email\": \"donald@gmail.com\",\n  \"password\": \"sarpanch\"\n}",
                "form": []
            }
        },
        {
            "_id": "ffdaf52e-e97f-479b-a594-9ac4f28620b8",
            "colId": "66c6f162-c303-44d8-9ad3-b3a6641d2b80",
            "containerId": "",
            "name": "login",
            "url": "http://localhost:3000/api/auth/login",
            "method": "POST",
            "sortNum": 30000,
            "created": "2025-03-15T07:49:21.739Z",
            "modified": "2025-03-15T07:50:47.088Z",
            "headers": [
                {
                    "name": "Content-Type",
                    "value": "application/json"
                },
                {
                    "name": "auth-token",
                    "value": "eyJhbGciOiJIUzI1NiIsInR5cCI6IkpXVCJ9.eyJ1c2VyIjp7ImlkIjoiNjdkNTMwZDU4ZGYwYmU4ZTkwN2JjZjViIn0sImlhdCI6MTc0MjAyNDkxN30.V-MjpMjbLcFCSBy7cwcyrCarUk605k7KJwD0et5SXJU"
                }
            ],
            "body": {
                "type": "json",
                "raw": "{\n  \"email\": \"donald@gmail.com\",\n  \"password\": \"sarpanch\"\n}",
                "form": []
            }
        },
        {
            "_id": "901845d6-98d1-47ef-ab52-2b70c37e89c2",
            "colId": "66c6f162-c303-44d8-9ad3-b3a6641d2b80",
            "containerId": "",
            "name": "userdetails",
            "url": "http://localhost:3000/api/auth/userdetails",
            "method": "POST",
            "sortNum": 40000,
            "created": "2025-03-15T09:23:39.848Z",
            "modified": "2025-03-15T09:25:56.271Z",
            "headers": [
                {
                    "name": "Content-Type",
                    "value": "application/json"
                },
                {
                    "name": "auth-token",
                    "value": "eyJhbGciOiJIUzI1NiIsInR5cCI6IkpXVCJ9.eyJ1c2VyIjp7ImlkIjoiNjdkNTMwZDU4ZGYwYmU4ZTkwN2JjZjViIn0sImlhdCI6MTc0MjAyNDkxN30.V-MjpMjbLcFCSBy7cwcyrCarUk605k7KJwD0et5SXJU"
                }
            ]
        }
    ],
    "ref": "LF-q_fkyawqgy_coHC2aEBcWsLGarNAyOEVs5hNjIKsgOnU6b6C46VJENybcls2f1RyiYmKlEnB49R94PA8tOA"
}